log9.py
log9-0.2.dist-info/METADATA
log9-0.2.dist-info/WHEEL
log9-0.2.dist-info/top_level.txt
log9-0.2.dist-info/RECORD
