Metadata-Version: 2.1
Name: log9
Version: 0.2
Summary: 简单封装的彩色日志模块
Author: Tim-Saijun
Author-email: c@zair.top
Classifier: Programming Language :: Python :: 3
Classifier: License :: OSI Approved :: MIT License
Classifier: Operating System :: OS Independent
Requires-Dist: colorlog
